wren/__init__.py
wren/cli.py
wren/core.py
wren/http_server.py
wren/matrix.py
wren/telegram.py
wren_notes-0.4.0.dist-info/LICENSE
wren_notes-0.4.0.dist-info/METADATA
wren_notes-0.4.0.dist-info/WHEEL
wren_notes-0.4.0.dist-info/entry_points.txt
wren_notes-0.4.0.dist-info/top_level.txt
wren_notes-0.4.0.dist-info/RECORD
